imagi/__init__.py
imagi-0.0.0.dist-info/METADATA
imagi-0.0.0.dist-info/WHEEL
imagi-0.0.0.dist-info/top_level.txt
imagi-0.0.0.dist-info/RECORD
