Metadata-Version: 2.1
Name: imagi
Version: 0.0.0
Summary: Coming soon
Author: Ethan Xu
Author-email: ethan@waitblock.simplelogin.com
Classifier: Programming Language :: Python :: 3
Requires-Python: >=3.6
